{
  "meta": {
    "source": "LoLalytics",
    "region": "lan",
    "tier": "gold_plus",
    "window": "current",
    "min_pick_rate": 1.0,
    "allowed_tiers": [
      "A",
      "A+",
      "A-",
      "B+",
      "S",
      "S+",
      "S-"
    ],
    "generated_at_utc": "2026-03-21T07:14:37.406176+00:00",
    "is_partial": false,
    "failed_lanes": [],
    "warnings": [],
    "difficulty_method": "lane_relative_mastery_gap_pct_tertiles_v1",
    "rank_mode": "original_rank_plus_filtered_rank",
    "difficulty_colors": {
      "easy": "#5BC0FF",
      "medium": "#FFD54F",
      "hard": "#FF5A5F"
    }
  },
  "data": {
    "top": [
      {
        "lane": "top",
        "rank": 1,
        "name": "Singed",
        "icon_url": "https://cdn5.lolalytics.com/champx46/singed.webp",
        "champion_url": "https://lolalytics.com/lol/singed/build/?tier=gold_plus&region=lan",
        "tier": "S+",
        "win_rate": 55.81,
        "win_delta": 0.65,
        "pick_rate": 2.65,
        "ban_rate": 1.23,
        "pbi": 14,
        "delta": 1.71,
        "filtered_rank": 1,
        "best_win_est": 57.52,
        "mastery_gap_raw": 1.71,
        "mastery_gap_pct": 2.97,
        "difficulty": "easy",
        "difficulty_color": "#5BC0FF",
        "difficulty_order": 1
      },
      {
        "lane": "top",
        "rank": 2,
        "name": "Yone",
        "icon_url": "https://cdn5.lolalytics.com/champx46/yone.webp",
        "champion_url": "https://lolalytics.com/lol/yone/build/?lane=top&tier=gold_plus&region=lan",
        "tier": "S+",
        "win_rate": 52.05,
        "win_delta": 1.11,
        "pick_rate": 3.24,
        "ban_rate": 3.5,
        "pbi": 4,
        "delta": 5.29,
        "filtered_rank": 2,
        "best_win_est": 57.34,
        "mastery_gap_raw": 5.29,
        "mastery_gap_pct": 9.23,
        "difficulty": "medium",
        "difficulty_color": "#FFD54F",
        "difficulty_order": 2
      },
      {
        "lane": "top",
        "rank": 4,
        "name": "Kayle",
        "icon_url": "https://cdn5.lolalytics.com/champx46/kayle.webp",
        "champion_url": "https://lolalytics.com/lol/kayle/build/?tier=gold_plus&region=lan",
        "tier": "S",
        "win_rate": 54.24,
        "win_delta": 0.89,
        "pick_rate": 3.69,
        "ban_rate": 2.53,
        "pbi": 13,
        "delta": 3.24,
        "filtered_rank": 3,
        "best_win_est": 57.48,
        "mastery_gap_raw": 3.24,
        "mastery_gap_pct": 5.64,
        "difficulty": "easy",
        "difficulty_color": "#5BC0FF",
        "difficulty_order": 1
      },
      {
        "lane": "top",
        "rank": 5,
        "name": "Garen",
        "icon_url": "https://cdn5.lolalytics.com/champx46/garen.webp",
        "champion_url": "https://lolalytics.com/lol/garen/build/?tier=gold_plus&region=lan",
        "tier": "S",
        "win_rate": 54.17,
        "win_delta": 0.88,
        "pick_rate": 11.2,
        "ban_rate": 8.74,
        "pbi": 42,
        "delta": 4.15,
        "filtered_rank": 4,
        "best_win_est": 58.32,
        "mastery_gap_raw": 4.15,
        "mastery_gap_pct": 7.12,
        "difficulty": "easy",
        "difficulty_color": "#5BC0FF",
        "difficulty_order": 1
      },
      {
        "lane": "top",
        "rank": 7,
        "name": "Akali",
        "icon_url": "https://cdn5.lolalytics.com/champx46/akali.webp",
        "champion_url": "https://lolalytics.com/lol/akali/build/?lane=top&tier=gold_plus&region=lan",
        "tier": "S-",
        "win_rate": 51.8,
        "win_delta": 0.96,
        "pick_rate": 1.74,
        "ban_rate": 29.18,
        "pbi": 3,
        "delta": 4.52,
        "filtered_rank": 5,
        "best_win_est": 56.32,
        "mastery_gap_raw": 4.52,
        "mastery_gap_pct": 8.03,
        "difficulty": "medium",
        "difficulty_color": "#FFD54F",
        "difficulty_order": 2
      },
      {
        "lane": "top",
        "rank": 8,
        "name": "Jax",
        "icon_url": "https://cdn5.lolalytics.com/champx46/jax.webp",
        "champion_url": "https://lolalytics.com/lol/jax/build/?tier=gold_plus&region=lan",
        "tier": "S-",
        "win_rate": 51.96,
        "win_delta": 1.09,
        "pick_rate": 4.63,
        "ban_rate": 10.59,
        "pbi": 6,
        "delta": 4.18,
        "filtered_rank": 6,
        "best_win_est": 56.14,
        "mastery_gap_raw": 4.18,
        "mastery_gap_pct": 7.45,
        "difficulty": "medium",
        "difficulty_color": "#FFD54F",
        "difficulty_order": 2
      },
      {
        "lane": "top",
        "rank": 9,
        "name": "Sett",
        "icon_url": "https://cdn5.lolalytics.com/champx46/sett.webp",
        "champion_url": "https://lolalytics.com/lol/sett/build/?tier=gold_plus&region=lan",
        "tier": "A+",
        "win_rate": 52.86,
        "win_delta": 1.32,
        "pick_rate": 10.87,
        "ban_rate": 8.3,
        "pbi": 25,
        "delta": 4.92,
        "filtered_rank": 7,
        "best_win_est": 57.78,
        "mastery_gap_raw": 4.92,
        "mastery_gap_pct": 8.52,
        "difficulty": "medium",
        "difficulty_color": "#FFD54F",
        "difficulty_order": 2
      },
      {
        "lane": "top",
        "rank": 10,
        "name": "Mordekaiser",
        "icon_url": "https://cdn5.lolalytics.com/champx46/mordekaiser.webp",
        "champion_url": "https://lolalytics.com/lol/mordekaiser/build/?tier=gold_plus&region=lan",
        "tier": "A+",
        "win_rate": 53.22,
        "win_delta": 1.26,
        "pick_rate": 9.37,
        "ban_rate": 22.46,
        "pbi": 30,
        "delta": 4.58,
        "filtered_rank": 8,
        "best_win_est": 57.8,
        "mastery_gap_raw": 4.58,
        "mastery_gap_pct": 7.92,
        "difficulty": "medium",
        "difficulty_color": "#FFD54F",
        "difficulty_order": 2
      },
      {
        "lane": "top",
        "rank": 11,
        "name": "Zaahen",
        "icon_url": "https://cdn5.lolalytics.com/champx46/zaahen.webp",
        "champion_url": "https://lolalytics.com/lol/zaahen/build/?tier=gold_plus&region=lan",
        "tier": "A+",
        "win_rate": 50.65,
        "win_delta": 0.42,
        "pick_rate": 3.65,
        "ban_rate": 9.48,
        "pbi": 0,
        "delta": 5.77,
        "filtered_rank": 9,
        "best_win_est": 56.42,
        "mastery_gap_raw": 5.77,
        "mastery_gap_pct": 10.23,
        "difficulty": "hard",
        "difficulty_color": "#FF5A5F",
        "difficulty_order": 3
      },
      {
        "lane": "top",
        "rank": 12,
        "name": "Kennen",
        "icon_url": "https://cdn5.lolalytics.com/champx46/kennen.webp",
        "champion_url": "https://lolalytics.com/lol/kennen/build/?tier=gold_plus&region=lan",
        "tier": "A+",
        "win_rate": 51.23,
        "win_delta": 0.22,
        "pick_rate": 1.21,
        "ban_rate": 0.82,
        "pbi": 1,
        "delta": 5.84,
        "filtered_rank": 10,
        "best_win_est": 57.07,
        "mastery_gap_raw": 5.84,
        "mastery_gap_pct": 10.23,
        "difficulty": "hard",
        "difficulty_color": "#FF5A5F",
        "difficulty_order": 3
      },
      {
        "lane": "top",
        "rank": 15,
        "name": "Ornn",
        "icon_url": "https://cdn5.lolalytics.com/champx46/ornn.webp",
        "champion_url": "https://lolalytics.com/lol/ornn/build/?tier=gold_plus&region=lan",
        "tier": "A",
        "win_rate": 53.51,
        "win_delta": 0.78,
        "pick_rate": 6.05,
        "ban_rate": 1.65,
        "pbi": 17,
        "delta": 2.4,
        "filtered_rank": 11,
        "best_win_est": 55.91,
        "mastery_gap_raw": 2.4,
        "mastery_gap_pct": 4.29,
        "difficulty": "easy",
        "difficulty_color": "#5BC0FF",
        "difficulty_order": 1
      },
      {
        "lane": "top",
        "rank": 16,
        "name": "Vayne",
        "icon_url": "https://cdn5.lolalytics.com/champx46/vayne.webp",
        "champion_url": "https://lolalytics.com/lol/vayne/build/?lane=top&tier=gold_plus&region=lan",
        "tier": "A",
        "win_rate": 50.88,
        "win_delta": 0.7,
        "pick_rate": 2.16,
        "ban_rate": 11.38,
        "pbi": 0,
        "delta": 7.98,
        "filtered_rank": 12,
        "best_win_est": 58.86,
        "mastery_gap_raw": 7.98,
        "mastery_gap_pct": 13.56,
        "difficulty": "hard",
        "difficulty_color": "#FF5A5F",
        "difficulty_order": 3
      },
      {
        "lane": "top",
        "rank": 17,
        "name": "Shen",
        "icon_url": "https://cdn5.lolalytics.com/champx46/shen.webp",
        "champion_url": "https://lolalytics.com/lol/shen/build/?tier=gold_plus&region=lan",
        "tier": "A",
        "win_rate": 50.97,
        "win_delta": 0.96,
        "pick_rate": 4.26,
        "ban_rate": 3.49,
        "pbi": 1,
        "delta": 5.36,
        "filtered_rank": 13,
        "best_win_est": 56.33,
        "mastery_gap_raw": 5.36,
        "mastery_gap_pct": 9.52,
        "difficulty": "hard",
        "difficulty_color": "#FF5A5F",
        "difficulty_order": 3
      },
      {
        "lane": "top",
        "rank": 22,
        "name": "Urgot",
        "icon_url": "https://cdn5.lolalytics.com/champx46/urgot.webp",
        "champion_url": "https://lolalytics.com/lol/urgot/build/?tier=gold_plus&region=lan",
        "tier": "A-",
        "win_rate": 52.38,
        "win_delta": 0.75,
        "pick_rate": 3.6,
        "ban_rate": 1.45,
        "pbi": 6,
        "delta": 3.11,
        "filtered_rank": 14,
        "best_win_est": 55.49,
        "mastery_gap_raw": 3.11,
        "mastery_gap_pct": 5.6,
        "difficulty": "easy",
        "difficulty_color": "#5BC0FF",
        "difficulty_order": 1
      },
      {
        "lane": "top",
        "rank": 25,
        "name": "Gragas",
        "icon_url": "https://cdn5.lolalytics.com/champx46/gragas.webp",
        "champion_url": "https://lolalytics.com/lol/gragas/build/?tier=gold_plus&region=lan",
        "tier": "A-",
        "win_rate": 50.87,
        "win_delta": 0.7,
        "pick_rate": 1.36,
        "ban_rate": 0.45,
        "pbi": 0,
        "delta": 5.21,
        "filtered_rank": 15,
        "best_win_est": 56.08,
        "mastery_gap_raw": 5.21,
        "mastery_gap_pct": 9.29,
        "difficulty": "medium",
        "difficulty_color": "#FFD54F",
        "difficulty_order": 2
      },
      {
        "lane": "top",
        "rank": 26,
        "name": "Pantheon",
        "icon_url": "https://cdn5.lolalytics.com/champx46/pantheon.webp",
        "champion_url": "https://lolalytics.com/lol/pantheon/build/?lane=top&tier=gold_plus&region=lan",
        "tier": "A-",
        "win_rate": 51.06,
        "win_delta": 0.6,
        "pick_rate": 2.18,
        "ban_rate": 3.28,
        "pbi": 1,
        "delta": 4.1,
        "filtered_rank": 16,
        "best_win_est": 55.16,
        "mastery_gap_raw": 4.1,
        "mastery_gap_pct": 7.43,
        "difficulty": "easy",
        "difficulty_color": "#5BC0FF",
        "difficulty_order": 1
      },
      {
        "lane": "top",
        "rank": 27,
        "name": "Dr. Mundo",
        "icon_url": "https://cdn5.lolalytics.com/champx46/drmundo.webp",
        "champion_url": "https://lolalytics.com/lol/drmundo/build/?tier=gold_plus&region=lan",
        "tier": "B+",
        "win_rate": 50.58,
        "win_delta": 1.38,
        "pick_rate": 3.96,
        "ban_rate": 9.6,
        "pbi": -1,
        "delta": 5.14,
        "filtered_rank": 17,
        "best_win_est": 55.72,
        "mastery_gap_raw": 5.14,
        "mastery_gap_pct": 9.22,
        "difficulty": "medium",
        "difficulty_color": "#FFD54F",
        "difficulty_order": 2
      },
      {
        "lane": "top",
        "rank": 28,
        "name": "Olaf",
        "icon_url": "https://cdn5.lolalytics.com/champx46/olaf.webp",
        "champion_url": "https://lolalytics.com/lol/olaf/build/?tier=gold_plus&region=lan",
        "tier": "B+",
        "win_rate": 50.2,
        "win_delta": 1.31,
        "pick_rate": 1.76,
        "ban_rate": 1.02,
        "pbi": -1,
        "delta": 6.85,
        "filtered_rank": 18,
        "best_win_est": 57.05,
        "mastery_gap_raw": 6.85,
        "mastery_gap_pct": 12.01,
        "difficulty": "hard",
        "difficulty_color": "#FF5A5F",
        "difficulty_order": 3
      },
      {
        "lane": "top",
        "rank": 29,
        "name": "Nasus",
        "icon_url": "https://cdn5.lolalytics.com/champx46/nasus.webp",
        "champion_url": "https://lolalytics.com/lol/nasus/build/?tier=gold_plus&region=lan",
        "tier": "B+",
        "win_rate": 50.81,
        "win_delta": 0.95,
        "pick_rate": 5.14,
        "ban_rate": 7.72,
        "pbi": 0,
        "delta": 5.4,
        "filtered_rank": 19,
        "best_win_est": 56.21,
        "mastery_gap_raw": 5.4,
        "mastery_gap_pct": 9.61,
        "difficulty": "hard",
        "difficulty_color": "#FF5A5F",
        "difficulty_order": 3
      },
      {
        "lane": "top",
        "rank": 30,
        "name": "Jayce",
        "icon_url": "https://cdn5.lolalytics.com/champx46/jayce.webp",
        "champion_url": "https://lolalytics.com/lol/jayce/build/?tier=gold_plus&region=lan",
        "tier": "B+",
        "win_rate": 48.4,
        "win_delta": 0.68,
        "pick_rate": 1.48,
        "ban_rate": 0.66,
        "pbi": -4,
        "delta": 9.31,
        "filtered_rank": 20,
        "best_win_est": 57.71,
        "mastery_gap_raw": 9.31,
        "mastery_gap_pct": 16.13,
        "difficulty": "hard",
        "difficulty_color": "#FF5A5F",
        "difficulty_order": 3
      },
      {
        "lane": "top",
        "rank": 31,
        "name": "Yorick",
        "icon_url": "https://cdn5.lolalytics.com/champx46/yorick.webp",
        "champion_url": "https://lolalytics.com/lol/yorick/build/?tier=gold_plus&region=lan",
        "tier": "B+",
        "win_rate": 52.81,
        "win_delta": 1.2,
        "pick_rate": 5.54,
        "ban_rate": 12.25,
        "pbi": 13,
        "delta": 2.28,
        "filtered_rank": 21,
        "best_win_est": 55.09,
        "mastery_gap_raw": 2.28,
        "mastery_gap_pct": 4.14,
        "difficulty": "easy",
        "difficulty_color": "#5BC0FF",
        "difficulty_order": 1
      },
      {
        "lane": "top",
        "rank": 32,
        "name": "Sion",
        "icon_url": "https://cdn5.lolalytics.com/champx46/sion.webp",
        "champion_url": "https://lolalytics.com/lol/sion/build/?tier=gold_plus&region=lan",
        "tier": "B+",
        "win_rate": 50.76,
        "win_delta": 1.0,
        "pick_rate": 4.42,
        "ban_rate": 0.67,
        "pbi": 0,
        "delta": 4.89,
        "filtered_rank": 22,
        "best_win_est": 55.65,
        "mastery_gap_raw": 4.89,
        "mastery_gap_pct": 8.79,
        "difficulty": "medium",
        "difficulty_color": "#FFD54F",
        "difficulty_order": 2
      },
      {
        "lane": "top",
        "rank": 33,
        "name": "Malphite",
        "icon_url": "https://cdn5.lolalytics.com/champx46/malphite.webp",
        "champion_url": "https://lolalytics.com/lol/malphite/build/?tier=gold_plus&region=lan",
        "tier": "B+",
        "win_rate": 52.01,
        "win_delta": 0.69,
        "pick_rate": 5.69,
        "ban_rate": 19.75,
        "pbi": 9,
        "delta": 3.47,
        "filtered_rank": 23,
        "best_win_est": 55.48,
        "mastery_gap_raw": 3.47,
        "mastery_gap_pct": 6.25,
        "difficulty": "easy",
        "difficulty_color": "#5BC0FF",
        "difficulty_order": 1
      }
    ],
    "jungle": [
      {
        "lane": "jungle",
        "rank": 1,
        "name": "Viego",
        "icon_url": "https://cdn5.lolalytics.com/champx46/viego.webp",
        "champion_url": "https://lolalytics.com/lol/viego/build/?tier=gold_plus&region=lan",
        "tier": "S+",
        "win_rate": 51.58,
        "win_delta": 0.75,
        "pick_rate": 11.56,
        "ban_rate": 14.28,
        "pbi": 11,
        "delta": 6.21,
        "filtered_rank": 1,
        "best_win_est": 57.79,
        "mastery_gap_raw": 6.21,
        "mastery_gap_pct": 10.75,
        "difficulty": "hard",
        "difficulty_color": "#FF5A5F",
        "difficulty_order": 3
      },
      {
        "lane": "jungle",
        "rank": 2,
        "name": "Graves",
        "icon_url": "https://cdn5.lolalytics.com/champx46/graves.webp",
        "champion_url": "https://lolalytics.com/lol/graves/build/?tier=gold_plus&region=lan",
        "tier": "S+",
        "win_rate": 51.18,
        "win_delta": 0.26,
        "pick_rate": 13.7,
        "ban_rate": 9.14,
        "pbi": 6,
        "delta": 7.7,
        "filtered_rank": 2,
        "best_win_est": 58.88,
        "mastery_gap_raw": 7.7,
        "mastery_gap_pct": 13.08,
        "difficulty": "hard",
        "difficulty_color": "#FF5A5F",
        "difficulty_order": 3
      },
      {
        "lane": "jungle",
        "rank": 3,
        "name": "Nunu & Willump",
        "icon_url": "https://cdn5.lolalytics.com/champx46/nunu.webp",
        "champion_url": "https://lolalytics.com/lol/nunu/build/?tier=gold_plus&region=lan",
        "tier": "S",
        "win_rate": 52.93,
        "win_delta": null,
        "pick_rate": 1.78,
        "ban_rate": 0.29,
        "pbi": 4,
        "delta": 4.44,
        "filtered_rank": 3,
        "best_win_est": 57.37,
        "mastery_gap_raw": 4.44,
        "mastery_gap_pct": 7.74,
        "difficulty": "medium",
        "difficulty_color": "#FFD54F",
        "difficulty_order": 2
      },
      {
        "lane": "jungle",
        "rank": 5,
        "name": "Briar",
        "icon_url": "https://cdn5.lolalytics.com/champx46/briar.webp",
        "champion_url": "https://lolalytics.com/lol/briar/build/?tier=gold_plus&region=lan",
        "tier": "S",
        "win_rate": 54.18,
        "win_delta": 0.99,
        "pick_rate": 7.66,
        "ban_rate": 25.34,
        "pbi": 35,
        "delta": 2.89,
        "filtered_rank": 4,
        "best_win_est": 57.07,
        "mastery_gap_raw": 2.89,
        "mastery_gap_pct": 5.06,
        "difficulty": "easy",
        "difficulty_color": "#5BC0FF",
        "difficulty_order": 1
      },
      {
        "lane": "jungle",
        "rank": 6,
        "name": "Jarvan IV",
        "icon_url": "https://cdn5.lolalytics.com/champx46/jarvaniv.webp",
        "champion_url": "https://lolalytics.com/lol/jarvaniv/build/?tier=gold_plus&region=lan",
        "tier": "S-",
        "win_rate": 51.4,
        "win_delta": 0.66,
        "pick_rate": 2.85,
        "ban_rate": 0.77,
        "pbi": 2,
        "delta": 6.27,
        "filtered_rank": 5,
        "best_win_est": 57.67,
        "mastery_gap_raw": 6.27,
        "mastery_gap_pct": 10.87,
        "difficulty": "hard",
        "difficulty_color": "#FF5A5F",
        "difficulty_order": 3
      },
      {
        "lane": "jungle",
        "rank": 7,
        "name": "Master Yi",
        "icon_url": "https://cdn5.lolalytics.com/champx46/masteryi.webp",
        "champion_url": "https://lolalytics.com/lol/masteryi/build/?tier=gold_plus&region=lan",
        "tier": "S-",
        "win_rate": 52.69,
        "win_delta": 0.98,
        "pick_rate": 6.29,
        "ban_rate": 17.89,
        "pbi": 15,
        "delta": 4.26,
        "filtered_rank": 6,
        "best_win_est": 56.95,
        "mastery_gap_raw": 4.26,
        "mastery_gap_pct": 7.48,
        "difficulty": "easy",
        "difficulty_color": "#5BC0FF",
        "difficulty_order": 1
      },
      {
        "lane": "jungle",
        "rank": 9,
        "name": "Sylas",
        "icon_url": "https://cdn5.lolalytics.com/champx46/sylas.webp",
        "champion_url": "https://lolalytics.com/lol/sylas/build/?lane=jungle&tier=gold_plus&region=lan",
        "tier": "A+",
        "win_rate": 50.77,
        "win_delta": 0.45,
        "pick_rate": 4.44,
        "ban_rate": 9.49,
        "pbi": 0,
        "delta": 6.2,
        "filtered_rank": 7,
        "best_win_est": 56.97,
        "mastery_gap_raw": 6.2,
        "mastery_gap_pct": 10.88,
        "difficulty": "hard",
        "difficulty_color": "#FF5A5F",
        "difficulty_order": 3
      },
      {
        "lane": "jungle",
        "rank": 10,
        "name": "Xin Zhao",
        "icon_url": "https://cdn5.lolalytics.com/champx46/xinzhao.webp",
        "champion_url": "https://lolalytics.com/lol/xinzhao/build/?tier=gold_plus&region=lan",
        "tier": "A+",
        "win_rate": 51.42,
        "win_delta": 0.57,
        "pick_rate": 2.84,
        "ban_rate": 0.98,
        "pbi": 2,
        "delta": 5.36,
        "filtered_rank": 8,
        "best_win_est": 56.78,
        "mastery_gap_raw": 5.36,
        "mastery_gap_pct": 9.44,
        "difficulty": "medium",
        "difficulty_color": "#FFD54F",
        "difficulty_order": 2
      },
      {
        "lane": "jungle",
        "rank": 11,
        "name": "Jax",
        "icon_url": "https://cdn5.lolalytics.com/champx46/jax.webp",
        "champion_url": "https://lolalytics.com/lol/jax/build/?lane=jungle&tier=gold_plus&region=lan",
        "tier": "A+",
        "win_rate": 51.61,
        "win_delta": 0.65,
        "pick_rate": 3.98,
        "ban_rate": 10.59,
        "pbi": 4,
        "delta": 4.53,
        "filtered_rank": 9,
        "best_win_est": 56.14,
        "mastery_gap_raw": 4.53,
        "mastery_gap_pct": 8.07,
        "difficulty": "medium",
        "difficulty_color": "#FFD54F",
        "difficulty_order": 2
      },
      {
        "lane": "jungle",
        "rank": 12,
        "name": "Amumu",
        "icon_url": "https://cdn5.lolalytics.com/champx46/amumu.webp",
        "champion_url": "https://lolalytics.com/lol/amumu/build/?tier=gold_plus&region=lan",
        "tier": "A+",
        "win_rate": 54.93,
        "win_delta": 1.89,
        "pick_rate": 3.09,
        "ban_rate": 2.22,
        "pbi": 13,
        "delta": 2.69,
        "filtered_rank": 10,
        "best_win_est": 57.62,
        "mastery_gap_raw": 2.69,
        "mastery_gap_pct": 4.67,
        "difficulty": "easy",
        "difficulty_color": "#5BC0FF",
        "difficulty_order": 1
      },
      {
        "lane": "jungle",
        "rank": 13,
        "name": "Shen",
        "icon_url": "https://cdn5.lolalytics.com/champx46/shen.webp",
        "champion_url": "https://lolalytics.com/lol/shen/build/?lane=jungle&tier=gold_plus&region=lan",
        "tier": "A",
        "win_rate": 52.1,
        "win_delta": 0.46,
        "pick_rate": 3.38,
        "ban_rate": 3.49,
        "pbi": 5,
        "delta": 4.23,
        "filtered_rank": 11,
        "best_win_est": 56.33,
        "mastery_gap_raw": 4.23,
        "mastery_gap_pct": 7.51,
        "difficulty": "medium",
        "difficulty_color": "#FFD54F",
        "difficulty_order": 2
      },
      {
        "lane": "jungle",
        "rank": 14,
        "name": "Dr. Mundo",
        "icon_url": "https://cdn5.lolalytics.com/champx46/drmundo.webp",
        "champion_url": "https://lolalytics.com/lol/drmundo/build/?lane=jungle&tier=gold_plus&region=lan",
        "tier": "A",
        "win_rate": 52.92,
        "win_delta": 0.7,
        "pick_rate": 3.75,
        "ban_rate": 9.6,
        "pbi": 9,
        "delta": 2.8,
        "filtered_rank": 12,
        "best_win_est": 55.72,
        "mastery_gap_raw": 2.8,
        "mastery_gap_pct": 5.03,
        "difficulty": "easy",
        "difficulty_color": "#5BC0FF",
        "difficulty_order": 1
      },
      {
        "lane": "jungle",
        "rank": 15,
        "name": "Zaahen",
        "icon_url": "https://cdn5.lolalytics.com/champx46/zaahen.webp",
        "champion_url": "https://lolalytics.com/lol/zaahen/build/?lane=jungle&tier=gold_plus&region=lan",
        "tier": "A",
        "win_rate": 50.95,
        "win_delta": 0.42,
        "pick_rate": 2.69,
        "ban_rate": 9.48,
        "pbi": 1,
        "delta": 5.47,
        "filtered_rank": 13,
        "best_win_est": 56.42,
        "mastery_gap_raw": 5.47,
        "mastery_gap_pct": 9.7,
        "difficulty": "medium",
        "difficulty_color": "#FFD54F",
        "difficulty_order": 2
      },
      {
        "lane": "jungle",
        "rank": 16,
        "name": "Gwen",
        "icon_url": "https://cdn5.lolalytics.com/champx46/gwen.webp",
        "champion_url": "https://lolalytics.com/lol/gwen/build/?lane=jungle&tier=gold_plus&region=lan",
        "tier": "A",
        "win_rate": 51.91,
        "win_delta": 0.17,
        "pick_rate": 1.49,
        "ban_rate": 5.03,
        "pbi": 2,
        "delta": 4.44,
        "filtered_rank": 14,
        "best_win_est": 56.35,
        "mastery_gap_raw": 4.44,
        "mastery_gap_pct": 7.88,
        "difficulty": "medium",
        "difficulty_color": "#FFD54F",
        "difficulty_order": 2
      },
      {
        "lane": "jungle",
        "rank": 17,
        "name": "Ekko",
        "icon_url": "https://cdn5.lolalytics.com/champx46/ekko.webp",
        "champion_url": "https://lolalytics.com/lol/ekko/build/?lane=jungle&tier=gold_plus&region=lan",
        "tier": "A",
        "win_rate": 50.77,
        "win_delta": 0.73,
        "pick_rate": 4.22,
        "ban_rate": 4.75,
        "pbi": 0,
        "delta": 5.5,
        "filtered_rank": 15,
        "best_win_est": 56.27,
        "mastery_gap_raw": 5.5,
        "mastery_gap_pct": 9.77,
        "difficulty": "hard",
        "difficulty_color": "#FF5A5F",
        "difficulty_order": 3
      },
      {
        "lane": "jungle",
        "rank": 19,
        "name": "Vi",
        "icon_url": "https://cdn5.lolalytics.com/champx46/vi.webp",
        "champion_url": "https://lolalytics.com/lol/vi/build/?tier=gold_plus&region=lan",
        "tier": "A-",
        "win_rate": 51.44,
        "win_delta": 0.45,
        "pick_rate": 3.79,
        "ban_rate": 0.77,
        "pbi": 3,
        "delta": 5.22,
        "filtered_rank": 16,
        "best_win_est": 56.66,
        "mastery_gap_raw": 5.22,
        "mastery_gap_pct": 9.21,
        "difficulty": "medium",
        "difficulty_color": "#FFD54F",
        "difficulty_order": 2
      },
      {
        "lane": "jungle",
        "rank": 20,
        "name": "Kayn",
        "icon_url": "https://cdn5.lolalytics.com/champx46/kayn.webp",
        "champion_url": "https://lolalytics.com/lol/kayn/build/?tier=gold_plus&region=lan",
        "tier": "A-",
        "win_rate": 50.5,
        "win_delta": 0.69,
        "pick_rate": 11.53,
        "ban_rate": 10.44,
        "pbi": -3,
        "delta": 7.82,
        "filtered_rank": 17,
        "best_win_est": 58.32,
        "mastery_gap_raw": 7.82,
        "mastery_gap_pct": 13.41,
        "difficulty": "hard",
        "difficulty_color": "#FF5A5F",
        "difficulty_order": 3
      },
      {
        "lane": "jungle",
        "rank": 21,
        "name": "Ambessa",
        "icon_url": "https://cdn5.lolalytics.com/champx46/ambessa.webp",
        "champion_url": "https://lolalytics.com/lol/ambessa/build/?lane=jungle&tier=gold_plus&region=lan",
        "tier": "A-",
        "win_rate": 50.15,
        "win_delta": 0.42,
        "pick_rate": 2.31,
        "ban_rate": 6.13,
        "pbi": -2,
        "delta": 6.49,
        "filtered_rank": 18,
        "best_win_est": 56.64,
        "mastery_gap_raw": 6.49,
        "mastery_gap_pct": 11.46,
        "difficulty": "hard",
        "difficulty_color": "#FF5A5F",
        "difficulty_order": 3
      },
      {
        "lane": "jungle",
        "rank": 22,
        "name": "Fiddlesticks",
        "icon_url": "https://cdn5.lolalytics.com/champx46/fiddlesticks.webp",
        "champion_url": "https://lolalytics.com/lol/fiddlesticks/build/?tier=gold_plus&region=lan",
        "tier": "A-",
        "win_rate": 52.69,
        "win_delta": 0.89,
        "pick_rate": 4.06,
        "ban_rate": 3.24,
        "pbi": 8,
        "delta": 2.69,
        "filtered_rank": 19,
        "best_win_est": 55.38,
        "mastery_gap_raw": 2.69,
        "mastery_gap_pct": 4.86,
        "difficulty": "easy",
        "difficulty_color": "#5BC0FF",
        "difficulty_order": 1
      },
      {
        "lane": "jungle",
        "rank": 25,
        "name": "Rammus",
        "icon_url": "https://cdn5.lolalytics.com/champx46/rammus.webp",
        "champion_url": "https://lolalytics.com/lol/rammus/build/?tier=gold_plus&region=lan",
        "tier": "B+",
        "win_rate": 54.58,
        "win_delta": 1.24,
        "pick_rate": 1.86,
        "ban_rate": 4.88,
        "pbi": 7,
        "delta": 0.92,
        "filtered_rank": 20,
        "best_win_est": 55.5,
        "mastery_gap_raw": 0.92,
        "mastery_gap_pct": 1.66,
        "difficulty": "easy",
        "difficulty_color": "#5BC0FF",
        "difficulty_order": 1
      },
      {
        "lane": "jungle",
        "rank": 26,
        "name": "Zac",
        "icon_url": "https://cdn5.lolalytics.com/champx46/zac.webp",
        "champion_url": "https://lolalytics.com/lol/zac/build/?tier=gold_plus&region=lan",
        "tier": "B+",
        "win_rate": 51.48,
        "win_delta": 0.62,
        "pick_rate": 1.84,
        "ban_rate": 0.77,
        "pbi": 1,
        "delta": 4.15,
        "filtered_rank": 21,
        "best_win_est": 55.63,
        "mastery_gap_raw": 4.15,
        "mastery_gap_pct": 7.46,
        "difficulty": "easy",
        "difficulty_color": "#5BC0FF",
        "difficulty_order": 1
      },
      {
        "lane": "jungle",
        "rank": 28,
        "name": "Nocturne",
        "icon_url": "https://cdn5.lolalytics.com/champx46/nocturne.webp",
        "champion_url": "https://lolalytics.com/lol/nocturne/build/?tier=gold_plus&region=lan",
        "tier": "B+",
        "win_rate": 51.46,
        "win_delta": 0.49,
        "pick_rate": 6.83,
        "ban_rate": 9.33,
        "pbi": 5,
        "delta": 4.74,
        "filtered_rank": 22,
        "best_win_est": 56.2,
        "mastery_gap_raw": 4.74,
        "mastery_gap_pct": 8.43,
        "difficulty": "medium",
        "difficulty_color": "#FFD54F",
        "difficulty_order": 2
      },
      {
        "lane": "jungle",
        "rank": 30,
        "name": "Pantheon",
        "icon_url": "https://cdn5.lolalytics.com/champx46/pantheon.webp",
        "champion_url": "https://lolalytics.com/lol/pantheon/build/?lane=jungle&tier=gold_plus&region=lan",
        "tier": "B+",
        "win_rate": 52.22,
        "win_delta": 0.51,
        "pick_rate": 1.15,
        "ban_rate": 3.28,
        "pbi": 2,
        "delta": 2.94,
        "filtered_rank": 23,
        "best_win_est": 55.16,
        "mastery_gap_raw": 2.94,
        "mastery_gap_pct": 5.33,
        "difficulty": "easy",
        "difficulty_color": "#5BC0FF",
        "difficulty_order": 1
      }
    ],
    "middle": [
      {
        "lane": "middle",
        "rank": 2,
        "name": "Irelia",
        "icon_url": "https://cdn5.lolalytics.com/champx46/irelia.webp",
        "champion_url": "https://lolalytics.com/lol/irelia/build/?tier=gold_plus&region=lan",
        "tier": "S+",
        "win_rate": 52.81,
        "win_delta": 0.91,
        "pick_rate": 3.12,
        "ban_rate": 7.62,
        "pbi": 7,
        "delta": 5.3,
        "filtered_rank": 1,
        "best_win_est": 58.11,
        "mastery_gap_raw": 5.3,
        "mastery_gap_pct": 9.12,
        "difficulty": "medium",
        "difficulty_color": "#FFD54F",
        "difficulty_order": 2
      },
      {
        "lane": "middle",
        "rank": 3,
        "name": "Diana",
        "icon_url": "https://cdn5.lolalytics.com/champx46/diana.webp",
        "champion_url": "https://lolalytics.com/lol/diana/build/?tier=gold_plus&region=lan",
        "tier": "S",
        "win_rate": 52.13,
        "win_delta": 0.24,
        "pick_rate": 5.27,
        "ban_rate": 12.23,
        "pbi": 8,
        "delta": 5.86,
        "filtered_rank": 2,
        "best_win_est": 57.99,
        "mastery_gap_raw": 5.86,
        "mastery_gap_pct": 10.11,
        "difficulty": "hard",
        "difficulty_color": "#FF5A5F",
        "difficulty_order": 3
      },
      {
        "lane": "middle",
        "rank": 4,
        "name": "Ahri",
        "icon_url": "https://cdn5.lolalytics.com/champx46/ahri.webp",
        "champion_url": "https://lolalytics.com/lol/ahri/build/?tier=gold_plus&region=lan",
        "tier": "S",
        "win_rate": 51.23,
        "win_delta": 0.91,
        "pick_rate": 10.09,
        "ban_rate": 5.68,
        "pbi": 5,
        "delta": 6.38,
        "filtered_rank": 3,
        "best_win_est": 57.61,
        "mastery_gap_raw": 6.38,
        "mastery_gap_pct": 11.07,
        "difficulty": "hard",
        "difficulty_color": "#FF5A5F",
        "difficulty_order": 3
      },
      {
        "lane": "middle",
        "rank": 7,
        "name": "Lux",
        "icon_url": "https://cdn5.lolalytics.com/champx46/lux.webp",
        "champion_url": "https://lolalytics.com/lol/lux/build/?lane=middle&tier=gold_plus&region=lan",
        "tier": "S-",
        "win_rate": 52.64,
        "win_delta": 0.71,
        "pick_rate": 5.38,
        "ban_rate": 12.23,
        "pbi": 11,
        "delta": 4.36,
        "filtered_rank": 4,
        "best_win_est": 57.0,
        "mastery_gap_raw": 4.36,
        "mastery_gap_pct": 7.65,
        "difficulty": "easy",
        "difficulty_color": "#5BC0FF",
        "difficulty_order": 1
      },
      {
        "lane": "middle",
        "rank": 8,
        "name": "Xerath",
        "icon_url": "https://cdn5.lolalytics.com/champx46/xerath.webp",
        "champion_url": "https://lolalytics.com/lol/xerath/build/?tier=gold_plus&region=lan",
        "tier": "S-",
        "win_rate": 52.93,
        "win_delta": 1.01,
        "pick_rate": 3.45,
        "ban_rate": 2.62,
        "pbi": 8,
        "delta": 4.35,
        "filtered_rank": 5,
        "best_win_est": 57.28,
        "mastery_gap_raw": 4.35,
        "mastery_gap_pct": 7.59,
        "difficulty": "easy",
        "difficulty_color": "#5BC0FF",
        "difficulty_order": 1
      },
      {
        "lane": "middle",
        "rank": 9,
        "name": "Anivia",
        "icon_url": "https://cdn5.lolalytics.com/champx46/anivia.webp",
        "champion_url": "https://lolalytics.com/lol/anivia/build/?tier=gold_plus&region=lan",
        "tier": "S-",
        "win_rate": 52.16,
        "win_delta": 0.71,
        "pick_rate": 2.47,
        "ban_rate": 1.19,
        "pbi": 3,
        "delta": 4.46,
        "filtered_rank": 6,
        "best_win_est": 56.62,
        "mastery_gap_raw": 4.46,
        "mastery_gap_pct": 7.88,
        "difficulty": "easy",
        "difficulty_color": "#5BC0FF",
        "difficulty_order": 1
      },
      {
        "lane": "middle",
        "rank": 10,
        "name": "Akali",
        "icon_url": "https://cdn5.lolalytics.com/champx46/akali.webp",
        "champion_url": "https://lolalytics.com/lol/akali/build/?tier=gold_plus&region=lan",
        "tier": "A+",
        "win_rate": 51.07,
        "win_delta": 0.72,
        "pick_rate": 8.69,
        "ban_rate": 29.18,
        "pbi": 4,
        "delta": 5.25,
        "filtered_rank": 7,
        "best_win_est": 56.32,
        "mastery_gap_raw": 5.25,
        "mastery_gap_pct": 9.32,
        "difficulty": "medium",
        "difficulty_color": "#FFD54F",
        "difficulty_order": 2
      },
      {
        "lane": "middle",
        "rank": 12,
        "name": "Zoe",
        "icon_url": "https://cdn5.lolalytics.com/champx46/zoe.webp",
        "champion_url": "https://lolalytics.com/lol/zoe/build/?tier=gold_plus&region=lan",
        "tier": "A+",
        "win_rate": 51.08,
        "win_delta": 0.92,
        "pick_rate": 3.13,
        "ban_rate": 1.75,
        "pbi": 1,
        "delta": 6.04,
        "filtered_rank": 8,
        "best_win_est": 57.12,
        "mastery_gap_raw": 6.04,
        "mastery_gap_pct": 10.57,
        "difficulty": "hard",
        "difficulty_color": "#FF5A5F",
        "difficulty_order": 3
      },
      {
        "lane": "middle",
        "rank": 14,
        "name": "Aurelion Sol",
        "icon_url": "https://cdn5.lolalytics.com/champx46/aurelionsol.webp",
        "champion_url": "https://lolalytics.com/lol/aurelionsol/build/?tier=gold_plus&region=lan",
        "tier": "A+",
        "win_rate": 51.47,
        "win_delta": 0.34,
        "pick_rate": 3.52,
        "ban_rate": 1.31,
        "pbi": 2,
        "delta": 6.7,
        "filtered_rank": 9,
        "best_win_est": 58.17,
        "mastery_gap_raw": 6.7,
        "mastery_gap_pct": 11.52,
        "difficulty": "hard",
        "difficulty_color": "#FF5A5F",
        "difficulty_order": 3
      },
      {
        "lane": "middle",
        "rank": 15,
        "name": "Ekko",
        "icon_url": "https://cdn5.lolalytics.com/champx46/ekko.webp",
        "champion_url": "https://lolalytics.com/lol/ekko/build/?tier=gold_plus&region=lan",
        "tier": "A",
        "win_rate": 51.23,
        "win_delta": 1.13,
        "pick_rate": 5.31,
        "ban_rate": 4.75,
        "pbi": 3,
        "delta": 5.04,
        "filtered_rank": 10,
        "best_win_est": 56.27,
        "mastery_gap_raw": 5.04,
        "mastery_gap_pct": 8.96,
        "difficulty": "medium",
        "difficulty_color": "#FFD54F",
        "difficulty_order": 2
      },
      {
        "lane": "middle",
        "rank": 16,
        "name": "Fizz",
        "icon_url": "https://cdn5.lolalytics.com/champx46/fizz.webp",
        "champion_url": "https://lolalytics.com/lol/fizz/build/?tier=gold_plus&region=lan",
        "tier": "A",
        "win_rate": 53.27,
        "win_delta": 1.28,
        "pick_rate": 6.43,
        "ban_rate": 10.63,
        "pbi": 18,
        "delta": 3.48,
        "filtered_rank": 11,
        "best_win_est": 56.75,
        "mastery_gap_raw": 3.48,
        "mastery_gap_pct": 6.13,
        "difficulty": "easy",
        "difficulty_color": "#5BC0FF",
        "difficulty_order": 1
      },
      {
        "lane": "middle",
        "rank": 19,
        "name": "Annie",
        "icon_url": "https://cdn5.lolalytics.com/champx46/annie.webp",
        "champion_url": "https://lolalytics.com/lol/annie/build/?tier=gold_plus&region=lan",
        "tier": "A",
        "win_rate": 52.83,
        "win_delta": 0.14,
        "pick_rate": 2.49,
        "ban_rate": 0.76,
        "pbi": 5,
        "delta": 5.88,
        "filtered_rank": 12,
        "best_win_est": 58.71,
        "mastery_gap_raw": 5.88,
        "mastery_gap_pct": 10.02,
        "difficulty": "medium",
        "difficulty_color": "#FFD54F",
        "difficulty_order": 2
      },
      {
        "lane": "middle",
        "rank": 20,
        "name": "Naafiri",
        "icon_url": "https://cdn5.lolalytics.com/champx46/naafiri.webp",
        "champion_url": "https://lolalytics.com/lol/naafiri/build/?tier=gold_plus&region=lan",
        "tier": "A",
        "win_rate": 51.85,
        "win_delta": 1.01,
        "pick_rate": 3.61,
        "ban_rate": 9.74,
        "pbi": 4,
        "delta": 4.34,
        "filtered_rank": 13,
        "best_win_est": 56.19,
        "mastery_gap_raw": 4.34,
        "mastery_gap_pct": 7.72,
        "difficulty": "easy",
        "difficulty_color": "#5BC0FF",
        "difficulty_order": 1
      },
      {
        "lane": "middle",
        "rank": 22,
        "name": "Syndra",
        "icon_url": "https://cdn5.lolalytics.com/champx46/syndra.webp",
        "champion_url": "https://lolalytics.com/lol/syndra/build/?tier=gold_plus&region=lan",
        "tier": "A-",
        "win_rate": 51.25,
        "win_delta": 0.36,
        "pick_rate": 3.08,
        "ban_rate": 1.26,
        "pbi": 1,
        "delta": 5.31,
        "filtered_rank": 14,
        "best_win_est": 56.56,
        "mastery_gap_raw": 5.31,
        "mastery_gap_pct": 9.39,
        "difficulty": "medium",
        "difficulty_color": "#FFD54F",
        "difficulty_order": 2
      },
      {
        "lane": "middle",
        "rank": 23,
        "name": "Vex",
        "icon_url": "https://cdn5.lolalytics.com/champx46/vex.webp",
        "champion_url": "https://lolalytics.com/lol/vex/build/?tier=gold_plus&region=lan",
        "tier": "A-",
        "win_rate": 53.32,
        "win_delta": 1.44,
        "pick_rate": 3.71,
        "ban_rate": 3.6,
        "pbi": 10,
        "delta": 3.15,
        "filtered_rank": 15,
        "best_win_est": 56.47,
        "mastery_gap_raw": 3.15,
        "mastery_gap_pct": 5.58,
        "difficulty": "easy",
        "difficulty_color": "#5BC0FF",
        "difficulty_order": 1
      },
      {
        "lane": "middle",
        "rank": 25,
        "name": "Viktor",
        "icon_url": "https://cdn5.lolalytics.com/champx46/viktor.webp",
        "champion_url": "https://lolalytics.com/lol/viktor/build/?tier=gold_plus&region=lan",
        "tier": "A-",
        "win_rate": 51.1,
        "win_delta": 0.62,
        "pick_rate": 5.09,
        "ban_rate": 1.79,
        "pbi": 2,
        "delta": 5.7,
        "filtered_rank": 16,
        "best_win_est": 56.8,
        "mastery_gap_raw": 5.7,
        "mastery_gap_pct": 10.04,
        "difficulty": "medium",
        "difficulty_color": "#FFD54F",
        "difficulty_order": 2
      },
      {
        "lane": "middle",
        "rank": 26,
        "name": "Veigar",
        "icon_url": "https://cdn5.lolalytics.com/champx46/veigar.webp",
        "champion_url": "https://lolalytics.com/lol/veigar/build/?tier=gold_plus&region=lan",
        "tier": "A-",
        "win_rate": 52.5,
        "win_delta": 1.12,
        "pick_rate": 9.96,
        "ban_rate": 6.69,
        "pbi": 18,
        "delta": 3.66,
        "filtered_rank": 17,
        "best_win_est": 56.16,
        "mastery_gap_raw": 3.66,
        "mastery_gap_pct": 6.52,
        "difficulty": "easy",
        "difficulty_color": "#5BC0FF",
        "difficulty_order": 1
      },
      {
        "lane": "middle",
        "rank": 27,
        "name": "Mel",
        "icon_url": "https://cdn5.lolalytics.com/champx46/mel.webp",
        "champion_url": "https://lolalytics.com/lol/mel/build/?tier=gold_plus&region=lan",
        "tier": "A-",
        "win_rate": 51.2,
        "win_delta": 0.82,
        "pick_rate": 6.92,
        "ban_rate": 28.14,
        "pbi": 4,
        "delta": 5.3,
        "filtered_rank": 18,
        "best_win_est": 56.5,
        "mastery_gap_raw": 5.3,
        "mastery_gap_pct": 9.38,
        "difficulty": "medium",
        "difficulty_color": "#FFD54F",
        "difficulty_order": 2
      },
      {
        "lane": "middle",
        "rank": 30,
        "name": "Hwei",
        "icon_url": "https://cdn5.lolalytics.com/champx46/hwei.webp",
        "champion_url": "https://lolalytics.com/lol/hwei/build/?tier=gold_plus&region=lan",
        "tier": "B+",
        "win_rate": 51.42,
        "win_delta": 0.51,
        "pick_rate": 2.71,
        "ban_rate": 1.37,
        "pbi": 2,
        "delta": 5.58,
        "filtered_rank": 19,
        "best_win_est": 57.0,
        "mastery_gap_raw": 5.58,
        "mastery_gap_pct": 9.79,
        "difficulty": "medium",
        "difficulty_color": "#FFD54F",
        "difficulty_order": 2
      },
      {
        "lane": "middle",
        "rank": 31,
        "name": "Yasuo",
        "icon_url": "https://cdn5.lolalytics.com/champx46/yasuo.webp",
        "champion_url": "https://lolalytics.com/lol/yasuo/build/?tier=gold_plus&region=lan",
        "tier": "B+",
        "win_rate": 50.15,
        "win_delta": 0.77,
        "pick_rate": 9.64,
        "ban_rate": 13.39,
        "pbi": -7,
        "delta": 5.68,
        "filtered_rank": 20,
        "best_win_est": 55.83,
        "mastery_gap_raw": 5.68,
        "mastery_gap_pct": 10.17,
        "difficulty": "hard",
        "difficulty_color": "#FF5A5F",
        "difficulty_order": 3
      },
      {
        "lane": "middle",
        "rank": 33,
        "name": "Malzahar",
        "icon_url": "https://cdn5.lolalytics.com/champx46/malzahar.webp",
        "champion_url": "https://lolalytics.com/lol/malzahar/build/?tier=gold_plus&region=lan",
        "tier": "B+",
        "win_rate": 53.0,
        "win_delta": 0.74,
        "pick_rate": 10.05,
        "ban_rate": 29.98,
        "pbi": 32,
        "delta": 2.77,
        "filtered_rank": 21,
        "best_win_est": 55.77,
        "mastery_gap_raw": 2.77,
        "mastery_gap_pct": 4.97,
        "difficulty": "easy",
        "difficulty_color": "#5BC0FF",
        "difficulty_order": 1
      },
      {
        "lane": "middle",
        "rank": 36,
        "name": "Lissandra",
        "icon_url": "https://cdn5.lolalytics.com/champx46/lissandra.webp",
        "champion_url": "https://lolalytics.com/lol/lissandra/build/?tier=gold_plus&region=lan",
        "tier": "B+",
        "win_rate": 50.91,
        "win_delta": 0.62,
        "pick_rate": 3.18,
        "ban_rate": 1.44,
        "pbi": 0,
        "delta": 6.68,
        "filtered_rank": 22,
        "best_win_est": 57.59,
        "mastery_gap_raw": 6.68,
        "mastery_gap_pct": 11.6,
        "difficulty": "hard",
        "difficulty_color": "#FF5A5F",
        "difficulty_order": 3
      },
      {
        "lane": "middle",
        "rank": 37,
        "name": "Sylas",
        "icon_url": "https://cdn5.lolalytics.com/champx46/sylas.webp",
        "champion_url": "https://lolalytics.com/lol/sylas/build/?tier=gold_plus&region=lan",
        "tier": "B+",
        "win_rate": 49.71,
        "win_delta": 0.69,
        "pick_rate": 8.4,
        "ban_rate": 9.49,
        "pbi": -10,
        "delta": 7.26,
        "filtered_rank": 23,
        "best_win_est": 56.97,
        "mastery_gap_raw": 7.26,
        "mastery_gap_pct": 12.74,
        "difficulty": "hard",
        "difficulty_color": "#FF5A5F",
        "difficulty_order": 3
      }
    ],
    "bottom": [
      {
        "lane": "bottom",
        "rank": 1,
        "name": "Caitlyn",
        "icon_url": "https://cdn5.lolalytics.com/champx46/caitlyn.webp",
        "champion_url": "https://lolalytics.com/lol/caitlyn/build/?tier=gold_plus&region=lan",
        "tier": "S+",
        "win_rate": 51.33,
        "win_delta": 0.75,
        "pick_rate": 23.47,
        "ban_rate": 38.82,
        "pbi": 21,
        "delta": 6.41,
        "filtered_rank": 1,
        "best_win_est": 57.74,
        "mastery_gap_raw": 6.41,
        "mastery_gap_pct": 11.1,
        "difficulty": "hard",
        "difficulty_color": "#FF5A5F",
        "difficulty_order": 3
      },
      {
        "lane": "bottom",
        "rank": 3,
        "name": "Jinx",
        "icon_url": "https://cdn5.lolalytics.com/champx46/jinx.webp",
        "champion_url": "https://lolalytics.com/lol/jinx/build/?tier=gold_plus&region=lan",
        "tier": "S-",
        "win_rate": 51.8,
        "win_delta": 0.9,
        "pick_rate": 16.13,
        "ban_rate": 7.49,
        "pbi": 18,
        "delta": 4.93,
        "filtered_rank": 2,
        "best_win_est": 56.73,
        "mastery_gap_raw": 4.93,
        "mastery_gap_pct": 8.69,
        "difficulty": "medium",
        "difficulty_color": "#FFD54F",
        "difficulty_order": 2
      },
      {
        "lane": "bottom",
        "rank": 5,
        "name": "Vayne",
        "icon_url": "https://cdn5.lolalytics.com/champx46/vayne.webp",
        "champion_url": "https://lolalytics.com/lol/vayne/build/?tier=gold_plus&region=lan",
        "tier": "A+",
        "win_rate": 51.46,
        "win_delta": 0.38,
        "pick_rate": 9.58,
        "ban_rate": 11.38,
        "pbi": 7,
        "delta": 7.4,
        "filtered_rank": 3,
        "best_win_est": 58.86,
        "mastery_gap_raw": 7.4,
        "mastery_gap_pct": 12.57,
        "difficulty": "hard",
        "difficulty_color": "#FF5A5F",
        "difficulty_order": 3
      },
      {
        "lane": "bottom",
        "rank": 6,
        "name": "Senna",
        "icon_url": "https://cdn5.lolalytics.com/champx46/senna.webp",
        "champion_url": "https://lolalytics.com/lol/senna/build/?lane=bottom&tier=gold_plus&region=lan",
        "tier": "A+",
        "win_rate": 53.83,
        "win_delta": 1.18,
        "pick_rate": 1.35,
        "ban_rate": 0.79,
        "pbi": 4,
        "delta": 2.93,
        "filtered_rank": 4,
        "best_win_est": 56.76,
        "mastery_gap_raw": 2.93,
        "mastery_gap_pct": 5.16,
        "difficulty": "medium",
        "difficulty_color": "#FFD54F",
        "difficulty_order": 2
      },
      {
        "lane": "bottom",
        "rank": 7,
        "name": "Aphelios",
        "icon_url": "https://cdn5.lolalytics.com/champx46/aphelios.webp",
        "champion_url": "https://lolalytics.com/lol/aphelios/build/?tier=gold_plus&region=lan",
        "tier": "A",
        "win_rate": 50.41,
        "win_delta": 0.95,
        "pick_rate": 4.81,
        "ban_rate": 3.29,
        "pbi": -2,
        "delta": 6.55,
        "filtered_rank": 5,
        "best_win_est": 56.96,
        "mastery_gap_raw": 6.55,
        "mastery_gap_pct": 11.5,
        "difficulty": "hard",
        "difficulty_color": "#FF5A5F",
        "difficulty_order": 3
      },
      {
        "lane": "bottom",
        "rank": 8,
        "name": "Ashe",
        "icon_url": "https://cdn5.lolalytics.com/champx46/ashe.webp",
        "champion_url": "https://lolalytics.com/lol/ashe/build/?tier=gold_plus&region=lan",
        "tier": "A",
        "win_rate": 51.83,
        "win_delta": 0.41,
        "pick_rate": 11.56,
        "ban_rate": 3.36,
        "pbi": 13,
        "delta": 6.06,
        "filtered_rank": 6,
        "best_win_est": 57.89,
        "mastery_gap_raw": 6.06,
        "mastery_gap_pct": 10.47,
        "difficulty": "hard",
        "difficulty_color": "#FF5A5F",
        "difficulty_order": 3
      },
      {
        "lane": "bottom",
        "rank": 10,
        "name": "Twitch",
        "icon_url": "https://cdn5.lolalytics.com/champx46/twitch.webp",
        "champion_url": "https://lolalytics.com/lol/twitch/build/?tier=gold_plus&region=lan",
        "tier": "A-",
        "win_rate": 51.82,
        "win_delta": 0.81,
        "pick_rate": 6.76,
        "ban_rate": 8.16,
        "pbi": 8,
        "delta": 4.25,
        "filtered_rank": 7,
        "best_win_est": 56.07,
        "mastery_gap_raw": 4.25,
        "mastery_gap_pct": 7.58,
        "difficulty": "medium",
        "difficulty_color": "#FFD54F",
        "difficulty_order": 2
      },
      {
        "lane": "bottom",
        "rank": 13,
        "name": "Smolder",
        "icon_url": "https://cdn5.lolalytics.com/champx46/smolder.webp",
        "champion_url": "https://lolalytics.com/lol/smolder/build/?tier=gold_plus&region=lan",
        "tier": "A-",
        "win_rate": 52.98,
        "win_delta": 0.53,
        "pick_rate": 13.7,
        "ban_rate": 14.05,
        "pbi": 35,
        "delta": 2.87,
        "filtered_rank": 8,
        "best_win_est": 55.85,
        "mastery_gap_raw": 2.87,
        "mastery_gap_pct": 5.14,
        "difficulty": "easy",
        "difficulty_color": "#5BC0FF",
        "difficulty_order": 1
      },
      {
        "lane": "bottom",
        "rank": 14,
        "name": "Veigar",
        "icon_url": "https://cdn5.lolalytics.com/champx46/veigar.webp",
        "champion_url": "https://lolalytics.com/lol/veigar/build/?lane=bottom&tier=gold_plus&region=lan",
        "tier": "B+",
        "win_rate": 55.12,
        "win_delta": 0.5,
        "pick_rate": 1.68,
        "ban_rate": 6.69,
        "pbi": 8,
        "delta": 1.04,
        "filtered_rank": 9,
        "best_win_est": 56.16,
        "mastery_gap_raw": 1.04,
        "mastery_gap_pct": 1.85,
        "difficulty": "easy",
        "difficulty_color": "#5BC0FF",
        "difficulty_order": 1
      },
      {
        "lane": "bottom",
        "rank": 15,
        "name": "Jhin",
        "icon_url": "https://cdn5.lolalytics.com/champx46/jhin.webp",
        "champion_url": "https://lolalytics.com/lol/jhin/build/?tier=gold_plus&region=lan",
        "tier": "B+",
        "win_rate": 50.9,
        "win_delta": 0.65,
        "pick_rate": 21.84,
        "ban_rate": 7.1,
        "pbi": 3,
        "delta": 3.45,
        "filtered_rank": 10,
        "best_win_est": 54.35,
        "mastery_gap_raw": 3.45,
        "mastery_gap_pct": 6.35,
        "difficulty": "medium",
        "difficulty_color": "#FFD54F",
        "difficulty_order": 2
      },
      {
        "lane": "bottom",
        "rank": 16,
        "name": "Kog'Maw",
        "icon_url": "https://cdn5.lolalytics.com/champx46/kogmaw.webp",
        "champion_url": "https://lolalytics.com/lol/kogmaw/build/?tier=gold_plus&region=lan",
        "tier": "B+",
        "win_rate": 53.67,
        "win_delta": 0.45,
        "pick_rate": 2.02,
        "ban_rate": 0.76,
        "pbi": 6,
        "delta": 1.59,
        "filtered_rank": 11,
        "best_win_est": 55.26,
        "mastery_gap_raw": 1.59,
        "mastery_gap_pct": 2.88,
        "difficulty": "easy",
        "difficulty_color": "#5BC0FF",
        "difficulty_order": 1
      },
      {
        "lane": "bottom",
        "rank": 17,
        "name": "Miss Fortune",
        "icon_url": "https://cdn5.lolalytics.com/champx46/missfortune.webp",
        "champion_url": "https://lolalytics.com/lol/missfortune/build/?tier=gold_plus&region=lan",
        "tier": "B+",
        "win_rate": 52.59,
        "win_delta": 1.28,
        "pick_rate": 14.71,
        "ban_rate": 5.66,
        "pbi": 28,
        "delta": 2.74,
        "filtered_rank": 12,
        "best_win_est": 55.33,
        "mastery_gap_raw": 2.74,
        "mastery_gap_pct": 4.95,
        "difficulty": "easy",
        "difficulty_color": "#5BC0FF",
        "difficulty_order": 1
      }
    ],
    "support": [
      {
        "lane": "support",
        "rank": 1,
        "name": "Nami",
        "icon_url": "https://cdn5.lolalytics.com/champx46/nami.webp",
        "champion_url": "https://lolalytics.com/lol/nami/build/?tier=gold_plus&region=lan",
        "tier": "S+",
        "win_rate": 52.71,
        "win_delta": 0.33,
        "pick_rate": 13.3,
        "ban_rate": 5.54,
        "pbi": 27,
        "delta": 3.91,
        "filtered_rank": 1,
        "best_win_est": 56.62,
        "mastery_gap_raw": 3.91,
        "mastery_gap_pct": 6.91,
        "difficulty": "easy",
        "difficulty_color": "#5BC0FF",
        "difficulty_order": 1
      },
      {
        "lane": "support",
        "rank": 2,
        "name": "Sona",
        "icon_url": "https://cdn5.lolalytics.com/champx46/sona.webp",
        "champion_url": "https://lolalytics.com/lol/sona/build/?tier=gold_plus&region=lan",
        "tier": "S",
        "win_rate": 52.88,
        "win_delta": 0.23,
        "pick_rate": 4.13,
        "ban_rate": 0.28,
        "pbi": 9,
        "delta": 3.78,
        "filtered_rank": 2,
        "best_win_est": 56.66,
        "mastery_gap_raw": 3.78,
        "mastery_gap_pct": 6.67,
        "difficulty": "easy",
        "difficulty_color": "#5BC0FF",
        "difficulty_order": 1
      },
      {
        "lane": "support",
        "rank": 3,
        "name": "Thresh",
        "icon_url": "https://cdn5.lolalytics.com/champx46/thresh.webp",
        "champion_url": "https://lolalytics.com/lol/thresh/build/?tier=gold_plus&region=lan",
        "tier": "S",
        "win_rate": 51.05,
        "win_delta": 0.7,
        "pick_rate": 10.52,
        "ban_rate": 2.78,
        "pbi": 3,
        "delta": 6.0,
        "filtered_rank": 3,
        "best_win_est": 57.05,
        "mastery_gap_raw": 6.0,
        "mastery_gap_pct": 10.52,
        "difficulty": "hard",
        "difficulty_color": "#FF5A5F",
        "difficulty_order": 3
      },
      {
        "lane": "support",
        "rank": 4,
        "name": "Seraphine",
        "icon_url": "https://cdn5.lolalytics.com/champx46/seraphine.webp",
        "champion_url": "https://lolalytics.com/lol/seraphine/build/?tier=gold_plus&region=lan",
        "tier": "S",
        "win_rate": 52.48,
        "win_delta": 0.38,
        "pick_rate": 7.04,
        "ban_rate": 2.02,
        "pbi": 12,
        "delta": 3.46,
        "filtered_rank": 4,
        "best_win_est": 55.94,
        "mastery_gap_raw": 3.46,
        "mastery_gap_pct": 6.19,
        "difficulty": "easy",
        "difficulty_color": "#5BC0FF",
        "difficulty_order": 1
      },
      {
        "lane": "support",
        "rank": 5,
        "name": "Taric",
        "icon_url": "https://cdn5.lolalytics.com/champx46/taric.webp",
        "champion_url": "https://lolalytics.com/lol/taric/build/?tier=gold_plus&region=lan",
        "tier": "S-",
        "win_rate": 52.96,
        "win_delta": 0.52,
        "pick_rate": 2.18,
        "ban_rate": 0.51,
        "pbi": 5,
        "delta": 4.56,
        "filtered_rank": 5,
        "best_win_est": 57.52,
        "mastery_gap_raw": 4.56,
        "mastery_gap_pct": 7.93,
        "difficulty": "medium",
        "difficulty_color": "#FFD54F",
        "difficulty_order": 2
      },
      {
        "lane": "support",
        "rank": 6,
        "name": "Soraka",
        "icon_url": "https://cdn5.lolalytics.com/champx46/soraka.webp",
        "champion_url": "https://lolalytics.com/lol/soraka/build/?tier=gold_plus&region=lan",
        "tier": "S-",
        "win_rate": 51.13,
        "win_delta": 0.44,
        "pick_rate": 5.02,
        "ban_rate": 3.01,
        "pbi": 2,
        "delta": 5.9,
        "filtered_rank": 6,
        "best_win_est": 57.03,
        "mastery_gap_raw": 5.9,
        "mastery_gap_pct": 10.35,
        "difficulty": "hard",
        "difficulty_color": "#FF5A5F",
        "difficulty_order": 3
      },
      {
        "lane": "support",
        "rank": 7,
        "name": "Janna",
        "icon_url": "https://cdn5.lolalytics.com/champx46/janna.webp",
        "champion_url": "https://lolalytics.com/lol/janna/build/?tier=gold_plus&region=lan",
        "tier": "S-",
        "win_rate": 53.0,
        "win_delta": 0.39,
        "pick_rate": 2.49,
        "ban_rate": 0.29,
        "pbi": 6,
        "delta": 1.94,
        "filtered_rank": 7,
        "best_win_est": 54.94,
        "mastery_gap_raw": 1.94,
        "mastery_gap_pct": 3.53,
        "difficulty": "easy",
        "difficulty_color": "#5BC0FF",
        "difficulty_order": 1
      },
      {
        "lane": "support",
        "rank": 8,
        "name": "Milio",
        "icon_url": "https://cdn5.lolalytics.com/champx46/milio.webp",
        "champion_url": "https://lolalytics.com/lol/milio/build/?tier=gold_plus&region=lan",
        "tier": "A+",
        "win_rate": 53.57,
        "win_delta": 0.47,
        "pick_rate": 8.03,
        "ban_rate": 10.38,
        "pbi": 25,
        "delta": 1.95,
        "filtered_rank": 8,
        "best_win_est": 55.52,
        "mastery_gap_raw": 1.95,
        "mastery_gap_pct": 3.51,
        "difficulty": "easy",
        "difficulty_color": "#5BC0FF",
        "difficulty_order": 1
      },
      {
        "lane": "support",
        "rank": 11,
        "name": "Braum",
        "icon_url": "https://cdn5.lolalytics.com/champx46/braum.webp",
        "champion_url": "https://lolalytics.com/lol/braum/build/?tier=gold_plus&region=lan",
        "tier": "A",
        "win_rate": 51.56,
        "win_delta": 0.44,
        "pick_rate": 4.89,
        "ban_rate": 3.3,
        "pbi": 4,
        "delta": 4.22,
        "filtered_rank": 9,
        "best_win_est": 55.78,
        "mastery_gap_raw": 4.22,
        "mastery_gap_pct": 7.57,
        "difficulty": "medium",
        "difficulty_color": "#FFD54F",
        "difficulty_order": 2
      },
      {
        "lane": "support",
        "rank": 12,
        "name": "Leona",
        "icon_url": "https://cdn5.lolalytics.com/champx46/leona.webp",
        "champion_url": "https://lolalytics.com/lol/leona/build/?tier=gold_plus&region=lan",
        "tier": "A",
        "win_rate": 50.95,
        "win_delta": 0.85,
        "pick_rate": 7.55,
        "ban_rate": 7.43,
        "pbi": 1,
        "delta": 6.26,
        "filtered_rank": 10,
        "best_win_est": 57.21,
        "mastery_gap_raw": 6.26,
        "mastery_gap_pct": 10.94,
        "difficulty": "hard",
        "difficulty_color": "#FF5A5F",
        "difficulty_order": 3
      },
      {
        "lane": "support",
        "rank": 13,
        "name": "Maokai",
        "icon_url": "https://cdn5.lolalytics.com/champx46/maokai.webp",
        "champion_url": "https://lolalytics.com/lol/maokai/build/?tier=gold_plus&region=lan",
        "tier": "A",
        "win_rate": 52.51,
        "win_delta": 0.83,
        "pick_rate": 3.12,
        "ban_rate": 0.48,
        "pbi": 5,
        "delta": 4.17,
        "filtered_rank": 11,
        "best_win_est": 56.68,
        "mastery_gap_raw": 4.17,
        "mastery_gap_pct": 7.36,
        "difficulty": "medium",
        "difficulty_color": "#FFD54F",
        "difficulty_order": 2
      },
      {
        "lane": "support",
        "rank": 14,
        "name": "Swain",
        "icon_url": "https://cdn5.lolalytics.com/champx46/swain.webp",
        "champion_url": "https://lolalytics.com/lol/swain/build/?tier=gold_plus&region=lan",
        "tier": "A",
        "win_rate": 50.86,
        "win_delta": 1.39,
        "pick_rate": 5.16,
        "ban_rate": 4.82,
        "pbi": 0,
        "delta": 5.01,
        "filtered_rank": 12,
        "best_win_est": 55.87,
        "mastery_gap_raw": 5.01,
        "mastery_gap_pct": 8.97,
        "difficulty": "medium",
        "difficulty_color": "#FFD54F",
        "difficulty_order": 2
      },
      {
        "lane": "support",
        "rank": 15,
        "name": "Lux",
        "icon_url": "https://cdn5.lolalytics.com/champx46/lux.webp",
        "champion_url": "https://lolalytics.com/lol/lux/build/?tier=gold_plus&region=lan",
        "tier": "A",
        "win_rate": 50.27,
        "win_delta": 1.36,
        "pick_rate": 10.4,
        "ban_rate": 12.23,
        "pbi": -6,
        "delta": 6.73,
        "filtered_rank": 13,
        "best_win_est": 57.0,
        "mastery_gap_raw": 6.73,
        "mastery_gap_pct": 11.81,
        "difficulty": "hard",
        "difficulty_color": "#FF5A5F",
        "difficulty_order": 3
      },
      {
        "lane": "support",
        "rank": 16,
        "name": "Vel'Koz",
        "icon_url": "https://cdn5.lolalytics.com/champx46/velkoz.webp",
        "champion_url": "https://lolalytics.com/lol/velkoz/build/?tier=gold_plus&region=lan",
        "tier": "A",
        "win_rate": 51.32,
        "win_delta": 0.6,
        "pick_rate": 3.18,
        "ban_rate": 1.29,
        "pbi": 2,
        "delta": 4.85,
        "filtered_rank": 14,
        "best_win_est": 56.17,
        "mastery_gap_raw": 4.85,
        "mastery_gap_pct": 8.63,
        "difficulty": "medium",
        "difficulty_color": "#FFD54F",
        "difficulty_order": 2
      },
      {
        "lane": "support",
        "rank": 19,
        "name": "Shaco",
        "icon_url": "https://cdn5.lolalytics.com/champx46/shaco.webp",
        "champion_url": "https://lolalytics.com/lol/shaco/build/?lane=support&tier=gold_plus&region=lan",
        "tier": "A-",
        "win_rate": 52.0,
        "win_delta": 0.95,
        "pick_rate": 1.3,
        "ban_rate": 13.23,
        "pbi": 2,
        "delta": 3.76,
        "filtered_rank": 15,
        "best_win_est": 55.76,
        "mastery_gap_raw": 3.76,
        "mastery_gap_pct": 6.74,
        "difficulty": "easy",
        "difficulty_color": "#5BC0FF",
        "difficulty_order": 1
      },
      {
        "lane": "support",
        "rank": 20,
        "name": "Zilean",
        "icon_url": "https://cdn5.lolalytics.com/champx46/zilean.webp",
        "champion_url": "https://lolalytics.com/lol/zilean/build/?tier=gold_plus&region=lan",
        "tier": "A-",
        "win_rate": 51.24,
        "win_delta": 0.54,
        "pick_rate": 2.21,
        "ban_rate": 0.75,
        "pbi": 1,
        "delta": 4.96,
        "filtered_rank": 16,
        "best_win_est": 56.2,
        "mastery_gap_raw": 4.96,
        "mastery_gap_pct": 8.83,
        "difficulty": "medium",
        "difficulty_color": "#FFD54F",
        "difficulty_order": 2
      },
      {
        "lane": "support",
        "rank": 21,
        "name": "Lulu",
        "icon_url": "https://cdn5.lolalytics.com/champx46/lulu.webp",
        "champion_url": "https://lolalytics.com/lol/lulu/build/?tier=gold_plus&region=lan",
        "tier": "A-",
        "win_rate": 49.96,
        "win_delta": 0.17,
        "pick_rate": 6.55,
        "ban_rate": 6.04,
        "pbi": -6,
        "delta": 6.79,
        "filtered_rank": 17,
        "best_win_est": 56.75,
        "mastery_gap_raw": 6.79,
        "mastery_gap_pct": 11.96,
        "difficulty": "hard",
        "difficulty_color": "#FF5A5F",
        "difficulty_order": 3
      },
      {
        "lane": "support",
        "rank": 22,
        "name": "Senna",
        "icon_url": "https://cdn5.lolalytics.com/champx46/senna.webp",
        "champion_url": "https://lolalytics.com/lol/senna/build/?tier=gold_plus&region=lan",
        "tier": "B+",
        "win_rate": 50.37,
        "win_delta": 1.1,
        "pick_rate": 4.99,
        "ban_rate": 0.79,
        "pbi": -2,
        "delta": 6.39,
        "filtered_rank": 18,
        "best_win_est": 56.76,
        "mastery_gap_raw": 6.39,
        "mastery_gap_pct": 11.26,
        "difficulty": "hard",
        "difficulty_color": "#FF5A5F",
        "difficulty_order": 3
      },
      {
        "lane": "support",
        "rank": 23,
        "name": "Xerath",
        "icon_url": "https://cdn5.lolalytics.com/champx46/xerath.webp",
        "champion_url": "https://lolalytics.com/lol/xerath/build/?lane=support&tier=gold_plus&region=lan",
        "tier": "B+",
        "win_rate": 51.32,
        "win_delta": 1.12,
        "pick_rate": 2.74,
        "ban_rate": 2.62,
        "pbi": 2,
        "delta": 5.96,
        "filtered_rank": 19,
        "best_win_est": 57.28,
        "mastery_gap_raw": 5.96,
        "mastery_gap_pct": 10.41,
        "difficulty": "hard",
        "difficulty_color": "#FF5A5F",
        "difficulty_order": 3
      },
      {
        "lane": "support",
        "rank": 24,
        "name": "Brand",
        "icon_url": "https://cdn5.lolalytics.com/champx46/brand.webp",
        "champion_url": "https://lolalytics.com/lol/brand/build/?tier=gold_plus&region=lan",
        "tier": "B+",
        "win_rate": 53.8,
        "win_delta": 1.37,
        "pick_rate": 4.91,
        "ban_rate": 7.12,
        "pbi": 16,
        "delta": 1.3,
        "filtered_rank": 20,
        "best_win_est": 55.1,
        "mastery_gap_raw": 1.3,
        "mastery_gap_pct": 2.36,
        "difficulty": "easy",
        "difficulty_color": "#5BC0FF",
        "difficulty_order": 1
      },
      {
        "lane": "support",
        "rank": 25,
        "name": "Zyra",
        "icon_url": "https://cdn5.lolalytics.com/champx46/zyra.webp",
        "champion_url": "https://lolalytics.com/lol/zyra/build/?tier=gold_plus&region=lan",
        "tier": "B+",
        "win_rate": 51.45,
        "win_delta": 1.14,
        "pick_rate": 3.4,
        "ban_rate": 3.74,
        "pbi": 2,
        "delta": 4.05,
        "filtered_rank": 21,
        "best_win_est": 55.5,
        "mastery_gap_raw": 4.05,
        "mastery_gap_pct": 7.3,
        "difficulty": "easy",
        "difficulty_color": "#5BC0FF",
        "difficulty_order": 1
      },
      {
        "lane": "support",
        "rank": 26,
        "name": "Shen",
        "icon_url": "https://cdn5.lolalytics.com/champx46/shen.webp",
        "champion_url": "https://lolalytics.com/lol/shen/build/?lane=support&tier=gold_plus&region=lan",
        "tier": "B+",
        "win_rate": 50.91,
        "win_delta": 1.02,
        "pick_rate": 1.04,
        "ban_rate": 3.49,
        "pbi": 0,
        "delta": 5.42,
        "filtered_rank": 22,
        "best_win_est": 56.33,
        "mastery_gap_raw": 5.42,
        "mastery_gap_pct": 9.62,
        "difficulty": "medium",
        "difficulty_color": "#FFD54F",
        "difficulty_order": 2
      }
    ]
  }
}